{"responses":[{"others":[],"title":" Slardar. ","url":"http://hydra-media.cursecdn.com/dota2.gamepedia.com/b/b4/Slar_spawn_01.mp3"},{"others":[],"title":" I am Slardar. ","url":"http://hydra-media.cursecdn.com/dota2.gamepedia.com/a/a3/Slar_spawn_02.mp3"},{"others":[],"title":" From the deeps, I rise. ","url":"http://hydra-media.cursecdn.com/dota2.gamepedia.com/a/a1/Slar_spawn_03.mp3"},{"others":[],"title":" Guardian of the deeps. ","url":"http://hydra-media.cursecdn.com/dota2.gamepedia.com/4/4b/Slar_spawn_05.mp3"},{"others":[],"title":" The deep ones send me forth. ","url":"http://hydra-media.cursecdn.com/dota2.gamepedia.com/c/cc/Slar_spawn_04.mp3"},{"others":[],"title":" First blood, ehha hehee! ","url":"http://hydra-media.cursecdn.com/dota2.gamepedia.com/3/32/Slar_firstblood_01.mp3"},{"others":[],"title":" Yes! ","url":"http://hydra-media.cursecdn.com/dota2.gamepedia.com/c/ca/Slar_move_01.mp3"},{"others":[],"title":" Yes. ","url":"http://hydra-media.cursecdn.com/dota2.gamepedia.com/7/7b/Slar_move_02.mp3"},{"others":[],"title":" Hmmm. ","url":"http://hydra-media.cursecdn.com/dota2.gamepedia.com/4/4d/Slar_move_03.mp3"},{"others":[],"title":" Heeeeh. ","url":"http://hydra-media.cursecdn.com/dota2.gamepedia.com/3/3d/Slar_move_04.mp3"},{"others":[],"title":" Yes. ","url":"http://hydra-media.cursecdn.com/dota2.gamepedia.com/5/54/Slar_move_05.mp3"},{"others":[],"title":" Heeeahe. ","url":"http://hydra-media.cursecdn.com/dota2.gamepedia.com/b/be/Slar_move_06.mp3"},{"others":[],"title":" I go. ","url":"http://hydra-media.cursecdn.com/dota2.gamepedia.com/b/bc/Slar_move_07.mp3"},{"others":[],"title":" Patrolling. ","url":"http://hydra-media.cursecdn.com/dota2.gamepedia.com/6/61/Slar_move_08.mp3"},{"others":[],"title":" A swift current. ","url":"http://hydra-media.cursecdn.com/dota2.gamepedia.com/d/d6/Slar_move_09.mp3"},{"others":[],"title":" Slither. ","url":"http://hydra-media.cursecdn.com/dota2.gamepedia.com/7/76/Slar_move_10.mp3"},{"others":[],"title":" No delay. ","url":"http://hydra-media.cursecdn.com/dota2.gamepedia.com/2/27/Slar_move_11.mp3"},{"others":[],"title":" Rushing in. ","url":"http://hydra-media.cursecdn.com/dota2.gamepedia.com/5/5c/Slar_move_12.mp3"},{"others":[],"title":" Deep ones guide me. ","url":"http://hydra-media.cursecdn.com/dota2.gamepedia.com/a/aa/Slar_move_13.mp3"},{"others":[],"title":" Onward. ","url":"http://hydra-media.cursecdn.com/dota2.gamepedia.com/f/f8/Slar_move_14.mp3"},{"others":[],"title":" To the fight. ","url":"http://hydra-media.cursecdn.com/dota2.gamepedia.com/a/ad/Slar_move_15.mp3"},{"others":[],"title":" Guard well. ","url":"http://hydra-media.cursecdn.com/dota2.gamepedia.com/9/9c/Slar_move_16.mp3"},{"others":[],"title":" I rush to defend. ","url":"http://hydra-media.cursecdn.com/dota2.gamepedia.com/f/f4/Slar_move_17.mp3"},{"others":[],"title":" Attack! ","url":"http://hydra-media.cursecdn.com/dota2.gamepedia.com/9/91/Slar_attack_01.mp3"},{"others":[],"title":" On guard. ","url":"http://hydra-media.cursecdn.com/dota2.gamepedia.com/8/85/Slar_attack_02.mp3"},{"others":[],"title":" Vigilance! ","url":"http://hydra-media.cursecdn.com/dota2.gamepedia.com/9/91/Slar_attack_03.mp3"},{"others":[],"title":" After them. ","url":"http://hydra-media.cursecdn.com/dota2.gamepedia.com/7/74/Slar_attack_04.mp3"},{"others":[],"title":" On their tail. ","url":"http://hydra-media.cursecdn.com/dota2.gamepedia.com/6/6f/Slar_attack_05.mp3"},{"others":[],"title":" I\u0027m on to you. ","url":"http://hydra-media.cursecdn.com/dota2.gamepedia.com/0/06/Slar_attack_06.mp3"},{"others":[],"title":" No mercy. ","url":"http://hydra-media.cursecdn.com/dota2.gamepedia.com/3/34/Slar_attack_07.mp3"},{"others":[],"title":" Face me. ","url":"http://hydra-media.cursecdn.com/dota2.gamepedia.com/c/c1/Slar_attack_08.mp3"},{"others":[],"title":" Yeeeah, you\u0027re in deep water. ","url":"http://hydra-media.cursecdn.com/dota2.gamepedia.com/3/38/Slar_attack_09.mp3"},{"others":[],"title":" Cowards. ","url":"http://hydra-media.cursecdn.com/dota2.gamepedia.com/5/55/Slar_attack_10.mp3"},{"others":[],"title":" In over your head. ","url":"http://hydra-media.cursecdn.com/dota2.gamepedia.com/6/6d/Slar_attack_11.mp3"},{"others":[],"title":" Nee-sharneah ","url":"http://hydra-media.cursecdn.com/dota2.gamepedia.com/0/0d/Slar_attack_12.mp3"},{"others":[],"title":" No stopping me. ","url":"http://hydra-media.cursecdn.com/dota2.gamepedia.com/5/51/Slar_cast_01.mp3"},{"others":[],"title":" You won\u0027t escape. ","url":"http://hydra-media.cursecdn.com/dota2.gamepedia.com/d/d5/Slar_cast_02.mp3"},{"others":[],"title":" I give no quarter. ","url":"http://hydra-media.cursecdn.com/dota2.gamepedia.com/f/f3/Slar_cast_03.mp3"},{"others":[],"title":" Your armor melts away. ","url":"http://hydra-media.cursecdn.com/dota2.gamepedia.com/5/59/Slar_ability_ampdam_01.mp3"},{"others":[],"title":" Keep a lookout. ","url":"http://hydra-media.cursecdn.com/dota2.gamepedia.com/2/2f/Slar_ability_ampdam_02.mp3"},{"others":[],"title":" Look to the foe. ","url":"http://hydra-media.cursecdn.com/dota2.gamepedia.com/5/5a/Slar_ability_ampdam_03.mp3"},{"others":[],"title":" Revealed. ","url":"http://hydra-media.cursecdn.com/dota2.gamepedia.com/8/81/Slar_ability_ampdam_04.mp3"},{"others":[],"title":" Exposed your deceit. ","url":"http://hydra-media.cursecdn.com/dota2.gamepedia.com/2/20/Slar_ability_ampdam_05.mp3"},{"others":[],"title":" We see you. ","url":"http://hydra-media.cursecdn.com/dota2.gamepedia.com/4/4a/Slar_ability_ampdam_06.mp3"},{"others":[],"title":" Look there! ","url":"http://hydra-media.cursecdn.com/dota2.gamepedia.com/4/4a/Slar_ability_ampdam_07.mp3"},{"others":[],"title":" We seeee you. ","url":"http://hydra-media.cursecdn.com/dota2.gamepedia.com/c/cb/Slar_ability_ampdam_08.mp3"},{"others":[],"title":" I\u0027m onto you, Riki. ","url":"http://hydra-media.cursecdn.com/dota2.gamepedia.com/f/ff/Slar_ability_ampdam_09.mp3"},{"others":[],"title":" Riki\u0027s here! ","url":"http://hydra-media.cursecdn.com/dota2.gamepedia.com/3/30/Slar_ability_ampdam_10.mp3"},{"others":[],"title":" I\u0027ve got Riki. ","url":"http://hydra-media.cursecdn.com/dota2.gamepedia.com/b/be/Slar_ability_ampdam_11.mp3"},{"others":[],"title":" Riki revealed! ","url":"http://hydra-media.cursecdn.com/dota2.gamepedia.com/4/43/Slar_ability_ampdam_12.mp3"},{"others":[],"title":" Riki, you die. ","url":"http://hydra-media.cursecdn.com/dota2.gamepedia.com/0/0a/Slar_ability_ampdam_13.mp3"},{"others":[],"title":" Rikimaru, I see you. ","url":"http://hydra-media.cursecdn.com/dota2.gamepedia.com/e/ed/Slar_ability_ampdam_14.mp3"},{"others":[],"title":" I cross the world to take you down. ","url":"http://hydra-media.cursecdn.com/dota2.gamepedia.com/c/cd/Slar_longdistance_01.mp3"},{"others":[],"title":" Tsee heeh heh he he heh heh. ","url":"http://hydra-media.cursecdn.com/dota2.gamepedia.com/c/c9/Slar_longdistance_03.mp3"},{"others":[],"title":" Howa. ","url":"http://hydra-media.cursecdn.com/dota2.gamepedia.com/4/46/Slar_ability_failure_01.mp3"},{"others":[],"title":" Sseww. ","url":"http://hydra-media.cursecdn.com/dota2.gamepedia.com/6/66/Slar_ability_failure_02.mp3"},{"others":[],"title":" Nowa. ","url":"http://hydra-media.cursecdn.com/dota2.gamepedia.com/3/3d/Slar_ability_failure_03.mp3"},{"others":[],"title":" Scaling up! ","url":"http://hydra-media.cursecdn.com/dota2.gamepedia.com/f/ff/Slar_level_01.mp3"},{"others":[],"title":" My lure brightens! ","url":"http://hydra-media.cursecdn.com/dota2.gamepedia.com/8/8b/Slar_level_02.mp3"},{"others":[],"title":" My power grows! ","url":"http://hydra-media.cursecdn.com/dota2.gamepedia.com/8/89/Slar_level_03.mp3"},{"others":[],"title":" Packed to the gills! ","url":"http://hydra-media.cursecdn.com/dota2.gamepedia.com/5/55/Slar_level_04.mp3"},{"others":[],"title":" My strength increases. ","url":"http://hydra-media.cursecdn.com/dota2.gamepedia.com/4/49/Slar_level_05.mp3"},{"others":[],"title":" He hess he hess he hess. ","url":"http://hydra-media.cursecdn.com/dota2.gamepedia.com/c/c5/Slar_level_06.mp3"},{"others":[],"title":" He hess he hess he hess hes. ","url":"http://hydra-media.cursecdn.com/dota2.gamepedia.com/1/16/Slar_level_07.mp3"},{"others":[],"title":" Heeheheharghehh. ","url":"http://hydra-media.cursecdn.com/dota2.gamepedia.com/b/b4/Slar_kill_11.mp3"},{"others":[],"title":" I came a long way to see you die. ","url":"http://hydra-media.cursecdn.com/dota2.gamepedia.com/8/8b/Slar_longdistance_02.mp3"},{"others":[],"title":" My deepest sympathies. ","url":"http://hydra-media.cursecdn.com/dota2.gamepedia.com/3/35/Slar_kill_01.mp3"},{"others":[],"title":" Now you dwell in the deep! ","url":"http://hydra-media.cursecdn.com/dota2.gamepedia.com/1/1a/Slar_kill_02.mp3"},{"others":[],"title":" You were out of your depth. ","url":"http://hydra-media.cursecdn.com/dota2.gamepedia.com/2/28/Slar_kill_03.mp3"},{"others":[],"title":" Can\u0027t fathom why you thought you\u0027d survive. ","url":"http://hydra-media.cursecdn.com/dota2.gamepedia.com/c/c6/Slar_kill_04.mp3"},{"others":[],"title":" To the dead zone with you. ","url":"http://hydra-media.cursecdn.com/dota2.gamepedia.com/d/df/Slar_kill_05.mp3"},{"others":[],"title":" I killed you, but I\u0027ll not clean you. ","url":"http://hydra-media.cursecdn.com/dota2.gamepedia.com/3/39/Slar_kill_06.mp3"},{"others":[],"title":" Total spawnage. ","url":"http://hydra-media.cursecdn.com/dota2.gamepedia.com/3/32/Slar_kill_07.mp3"},{"others":[],"title":" Schooled you good. ","url":"http://hydra-media.cursecdn.com/dota2.gamepedia.com/b/b8/Slar_kill_08.mp3"},{"others":[],"title":" You let your guard down. ","url":"http://hydra-media.cursecdn.com/dota2.gamepedia.com/1/11/Slar_kill_09.mp3"},{"others":[],"title":" Hehehehhhehe. ","url":"http://hydra-media.cursecdn.com/dota2.gamepedia.com/e/e0/Slar_kill_10.mp3"},{"others":[],"title":" The treasures of the deep are safe from the likes of you. ","url":"http://hydra-media.cursecdn.com/dota2.gamepedia.com/d/d7/Slar_kill_12.mp3"},{"others":[],"title":" A soldier\u0027s fortune. ","url":"http://hydra-media.cursecdn.com/dota2.gamepedia.com/e/e6/Slar_lasthit_01.mp3"},{"others":[],"title":" Shiny as shoals. ","url":"http://hydra-media.cursecdn.com/dota2.gamepedia.com/6/6c/Slar_lasthit_02.mp3"},{"others":[],"title":" I\u0027ll treasure this. ","url":"http://hydra-media.cursecdn.com/dota2.gamepedia.com/a/a4/Slar_lasthit_03.mp3"},{"others":[],"title":" I\u0027ll do it for a fin. ","url":"http://hydra-media.cursecdn.com/dota2.gamepedia.com/a/a4/Slar_lasthit_04.mp3"},{"others":[],"title":" Tip the scales. ","url":"http://hydra-media.cursecdn.com/dota2.gamepedia.com/1/1c/Slar_lasthit_05.mp3"},{"others":[],"title":" Treasure for the deeps. ","url":"http://hydra-media.cursecdn.com/dota2.gamepedia.com/e/ee/Slar_lasthit_06.mp3"},{"others":[],"title":" To the deeps with you. ","url":"http://hydra-media.cursecdn.com/dota2.gamepedia.com/6/6d/Slar_lasthit_07.mp3"},{"others":[],"title":" Heheheeheehsss. ","url":"http://hydra-media.cursecdn.com/dota2.gamepedia.com/f/f5/Slar_lasthit_08.mp3"},{"others":[],"title":" Noooo. ","url":"http://hydra-media.cursecdn.com/dota2.gamepedia.com/f/f3/Slar_death_01.mp3"},{"others":[],"title":" Caught off guard. ","url":"http://hydra-media.cursecdn.com/dota2.gamepedia.com/2/24/Slar_death_02.mp3"},{"others":[],"title":" I\u0027ve failed in my duty. ","url":"http://hydra-media.cursecdn.com/dota2.gamepedia.com/2/2b/Slar_death_03.mp3"},{"others":[],"title":" Relieved of duty. ","url":"http://hydra-media.cursecdn.com/dota2.gamepedia.com/2/2e/Slar_death_04.mp3"},{"others":[],"title":" A lapse in vigilance. ","url":"http://hydra-media.cursecdn.com/dota2.gamepedia.com/5/5a/Slar_death_05.mp3"},{"others":[],"title":" I welcome the abyss. ","url":"http://hydra-media.cursecdn.com/dota2.gamepedia.com/1/12/Slar_death_06.mp3"},{"others":[],"title":" I hear the deep ones…calling. ","url":"http://hydra-media.cursecdn.com/dota2.gamepedia.com/2/2b/Slar_death_07.mp3"},{"others":[],"title":" Sub...merged. ","url":"http://hydra-media.cursecdn.com/dota2.gamepedia.com/b/bd/Slar_death_08.mp3"},{"others":[],"title":" I sound…the depths… ","url":"http://hydra-media.cursecdn.com/dota2.gamepedia.com/8/8d/Slar_death_09.mp3"},{"others":[],"title":" Slippery when…dead. ","url":"http://hydra-media.cursecdn.com/dota2.gamepedia.com/f/f1/Slar_death_10.mp3"},{"others":[],"title":" Into the black seas of infinity. ","url":"http://hydra-media.cursecdn.com/dota2.gamepedia.com/4/4b/Slar_death_11.mp3"},{"others":[],"title":" That is not dead that can eternal lie. ","url":"http://hydra-media.cursecdn.com/dota2.gamepedia.com/6/6d/Slar_death_12.mp3"},{"others":[],"title":" The last…of the old guard. ","url":"http://hydra-media.cursecdn.com/dota2.gamepedia.com/b/be/Slar_death_13.mp3"},{"others":[],"title":" Back to light and air. ","url":"http://hydra-media.cursecdn.com/dota2.gamepedia.com/1/1f/Slar_respawn_01.mp3"},{"others":[],"title":" And with strange eons even death may die. ","url":"http://hydra-media.cursecdn.com/dota2.gamepedia.com/0/03/Slar_respawn_02.mp3"},{"others":[],"title":" I soldier on. ","url":"http://hydra-media.cursecdn.com/dota2.gamepedia.com/9/93/Slar_respawn_03.mp3"},{"others":[],"title":" From lightless gulfs, I return. ","url":"http://hydra-media.cursecdn.com/dota2.gamepedia.com/f/f8/Slar_respawn_04.mp3"},{"others":[],"title":" Ah, my old spawning ground. ","url":"http://hydra-media.cursecdn.com/dota2.gamepedia.com/3/32/Slar_respawn_05.mp3"},{"others":[],"title":" Lured me back again. ","url":"http://hydra-media.cursecdn.com/dota2.gamepedia.com/e/e0/Slar_respawn_06.mp3"},{"others":[],"title":" I resurface. ","url":"http://hydra-media.cursecdn.com/dota2.gamepedia.com/e/e3/Slar_respawn_07.mp3"},{"others":[],"title":" I\u0027ll not be caught off guard again. ","url":"http://hydra-media.cursecdn.com/dota2.gamepedia.com/d/da/Slar_respawn_08.mp3"},{"others":[],"title":" The Centurion returns. ","url":"http://hydra-media.cursecdn.com/dota2.gamepedia.com/2/2a/Slar_respawn_09.mp3"},{"others":[],"title":" The deep ones return me to duty. ","url":"http://hydra-media.cursecdn.com/dota2.gamepedia.com/4/45/Slar_respawn_10.mp3"},{"others":[],"title":" Heh heeh heh hah hah ha hah hah! ","url":"http://hydra-media.cursecdn.com/dota2.gamepedia.com/9/90/Slar_laugh_05.mp3"},{"others":[],"title":" I guard what slumbers in the deeps. ","url":"http://hydra-media.cursecdn.com/dota2.gamepedia.com/7/7f/Slar_rare_01.mp3"},{"others":[],"title":" I\u0027m duty bound to defend the deep ones. ","url":"http://hydra-media.cursecdn.com/dota2.gamepedia.com/f/fe/Slar_rare_02.mp3"},{"others":[],"title":" The riches of the darkest sea abysses are mine to protect. ","url":"http://hydra-media.cursecdn.com/dota2.gamepedia.com/c/ce/Slar_rare_03.mp3"},{"others":[],"title":" Too bright up here and far too light. I long for the pressures of the deep, and the subtle luminosities of the sunken world. ","url":"http://hydra-media.cursecdn.com/dota2.gamepedia.com/a/a3/Slar_rare_04.mp3"},{"others":[],"title":" New treasures to guard. ","url":"http://hydra-media.cursecdn.com/dota2.gamepedia.com/f/f0/Slar_purch_01.mp3"},{"others":[],"title":" I will prize this with my life. ","url":"http://hydra-media.cursecdn.com/dota2.gamepedia.com/4/4e/Slar_purch_02.mp3"},{"others":[],"title":" This will make a splash. ","url":"http://hydra-media.cursecdn.com/dota2.gamepedia.com/c/ce/Slar_purch_03.mp3"},{"others":[],"title":" This would seem redundant. ","url":"http://hydra-media.cursecdn.com/dota2.gamepedia.com/1/1d/Slar_purch_basher_01.mp3"},{"others":[],"title":" Blink and you\u0027ll miss me. ","url":"http://hydra-media.cursecdn.com/dota2.gamepedia.com/5/5f/Slar_blink_01.mp3"},{"others":[],"title":" Blink dagger. ","url":"http://hydra-media.cursecdn.com/dota2.gamepedia.com/f/f3/Slar_blink_02.mp3"},{"others":[],"title":" I\u0027ll crush them in a blink. ","url":"http://hydra-media.cursecdn.com/dota2.gamepedia.com/a/aa/Slar_blink_03.mp3"},{"others":[],"title":" Ah, scepter. ","url":"http://hydra-media.cursecdn.com/dota2.gamepedia.com/1/1b/Slar_scepter_01.mp3"},{"others":[],"title":" A pearl beyond price. ","url":"http://hydra-media.cursecdn.com/dota2.gamepedia.com/d/d8/Slar_scepter_02.mp3"},{"others":[],"title":" Ah, divine rapier. ","url":"http://hydra-media.cursecdn.com/dota2.gamepedia.com/9/96/Slar_divine_01.mp3"},{"others":[],"title":" Ah, armlet. ","url":"http://hydra-media.cursecdn.com/dota2.gamepedia.com/8/8d/Slar_armlet_01.mp3"},{"others":[],"title":" Armlet drains me. ","url":"http://hydra-media.cursecdn.com/dota2.gamepedia.com/3/3b/Slar_armlet_02.mp3"},{"others":[],"title":" Armlet, dangerous even to me! ","url":"http://hydra-media.cursecdn.com/dota2.gamepedia.com/f/f8/Slar_armlet_03.mp3"},{"others":[],"title":" Armlet has reduced me. ","url":"http://hydra-media.cursecdn.com/dota2.gamepedia.com/6/6c/Slar_armlet_04.mp3"},{"others":[],"title":" I\u0027ll keep this under pressure. ","url":"http://hydra-media.cursecdn.com/dota2.gamepedia.com/5/5f/Slar_bottle_01.mp3"},{"others":[],"title":" Water tight to twenty fathoms. ","url":"http://hydra-media.cursecdn.com/dota2.gamepedia.com/f/f4/Slar_bottle_02.mp3"},{"others":[],"title":" I\u0027ll tap this later. ","url":"http://hydra-media.cursecdn.com/dota2.gamepedia.com/9/90/Slar_bottle_03.mp3"},{"others":[],"title":" Water tight. ","url":"http://hydra-media.cursecdn.com/dota2.gamepedia.com/c/c9/Slar_bottle_04.mp3"},{"others":[],"title":" Denied. ","url":"http://hydra-media.cursecdn.com/dota2.gamepedia.com/9/91/Slar_deny_01.mp3"},{"others":[],"title":" Uh uh. ","url":"http://hydra-media.cursecdn.com/dota2.gamepedia.com/9/9d/Slar_deny_02.mp3"},{"others":[],"title":" Uh uh. ","url":"http://hydra-media.cursecdn.com/dota2.gamepedia.com/f/f4/Slar_deny_03.mp3"},{"others":[],"title":" Cut bait. ","url":"http://hydra-media.cursecdn.com/dota2.gamepedia.com/b/bf/Slar_deny_04.mp3"},{"others":[],"title":" Jig\u0027s up. ","url":"http://hydra-media.cursecdn.com/dota2.gamepedia.com/7/71/Slar_deny_05.mp3"},{"others":[],"title":" You get nothing. ","url":"http://hydra-media.cursecdn.com/dota2.gamepedia.com/a/a8/Slar_deny_06.mp3"},{"others":[],"title":" He he heh heehwehe hehh. ","url":"http://hydra-media.cursecdn.com/dota2.gamepedia.com/9/9f/Slar_deny_07.mp3"},{"others":[],"title":" Not for you. ","url":"http://hydra-media.cursecdn.com/dota2.gamepedia.com/8/8b/Slar_deny_08.mp3"},{"others":[],"title":" No! ","url":"http://hydra-media.cursecdn.com/dota2.gamepedia.com/e/e3/Slar_lose_01.mp3"},{"others":[],"title":" Defeated! ","url":"http://hydra-media.cursecdn.com/dota2.gamepedia.com/9/94/Slar_lose_02.mp3"},{"others":[],"title":" Into the bottomless dark. ","url":"http://hydra-media.cursecdn.com/dota2.gamepedia.com/a/aa/Slar_lose_03.mp3"},{"others":[],"title":" Yes! ","url":"http://hydra-media.cursecdn.com/dota2.gamepedia.com/3/32/Slar_win_01.mp3"},{"others":[],"title":" Yeahs! ","url":"http://hydra-media.cursecdn.com/dota2.gamepedia.com/9/98/Slar_win_02.mp3"},{"others":[],"title":" Victory! ","url":"http://hydra-media.cursecdn.com/dota2.gamepedia.com/a/aa/Slar_win_03.mp3"},{"others":[],"title":" In the name of the nameless ones! ","url":"http://hydra-media.cursecdn.com/dota2.gamepedia.com/6/63/Slar_win_04.mp3"},{"others":[],"title":" Oh, how the deep ones will feast! ","url":"http://hydra-media.cursecdn.com/dota2.gamepedia.com/e/ed/Slar_win_05.mp3"},{"others":[],"title":" Immortality! ","url":"http://hydra-media.cursecdn.com/dota2.gamepedia.com/d/d6/Slar_immort_01.mp3"},{"others":[],"title":" Eternal life. ","url":"http://hydra-media.cursecdn.com/dota2.gamepedia.com/c/cb/Slar_immort_02.mp3"},{"others":[],"title":" Haste! ","url":"http://hydra-media.cursecdn.com/dota2.gamepedia.com/7/7e/Slar_haste_01.mp3"},{"others":[],"title":" I\u0027ll leave them all in my wake. ","url":"http://hydra-media.cursecdn.com/dota2.gamepedia.com/d/d3/Slar_haste_02.mp3"},{"others":[],"title":" Double damage! ","url":"http://hydra-media.cursecdn.com/dota2.gamepedia.com/2/23/Slar_doubdam_01.mp3"},{"others":[],"title":" Double duty. ","url":"http://hydra-media.cursecdn.com/dota2.gamepedia.com/b/b1/Slar_doubdam_02.mp3"},{"others":[],"title":" Regeneration! ","url":"http://hydra-media.cursecdn.com/dota2.gamepedia.com/e/ea/Slar_regen_01.mp3"},{"others":[],"title":" I regenerate. ","url":"http://hydra-media.cursecdn.com/dota2.gamepedia.com/4/4b/Slar_regen_02.mp3"},{"others":[],"title":" Illusion! ","url":"http://hydra-media.cursecdn.com/dota2.gamepedia.com/f/f3/Slar_illus_01.mp3"},{"others":[],"title":" A school of me. ","url":"http://hydra-media.cursecdn.com/dota2.gamepedia.com/6/67/Slar_illus_02.mp3"},{"others":[],"title":" Invisibility! ","url":"http://hydra-media.cursecdn.com/dota2.gamepedia.com/b/b6/Slar_invis_01.mp3"},{"others":[],"title":" Clear as clean water. ","url":"http://hydra-media.cursecdn.com/dota2.gamepedia.com/3/3e/Slar_invis_02.mp3"},{"others":[],"title":" A soldier\u0027s fortune. ","url":"http://hydra-media.cursecdn.com/dota2.gamepedia.com/e/e6/Slar_lasthit_01.mp3"},{"others":[],"title":" Not yet. ","url":"http://hydra-media.cursecdn.com/dota2.gamepedia.com/e/ef/Slar_notyet_01.mp3"},{"others":[],"title":" I\u0027m not ready. ","url":"http://hydra-media.cursecdn.com/dota2.gamepedia.com/2/2e/Slar_notyet_02.mp3"},{"others":[],"title":" It\u0027s not time yet. ","url":"http://hydra-media.cursecdn.com/dota2.gamepedia.com/7/72/Slar_notyet_03.mp3"},{"others":[],"title":" Not yet. ","url":"http://hydra-media.cursecdn.com/dota2.gamepedia.com/d/df/Slar_notyet_04.mp3"},{"others":[],"title":" I\u0027m not ready. ","url":"http://hydra-media.cursecdn.com/dota2.gamepedia.com/b/ba/Slar_notyet_05.mp3"},{"others":[],"title":" It\u0027s not time yet. ","url":"http://hydra-media.cursecdn.com/dota2.gamepedia.com/c/cb/Slar_notyet_06.mp3"},{"others":[],"title":" Not yet! ","url":"http://hydra-media.cursecdn.com/dota2.gamepedia.com/3/31/Slar_notyet_07.mp3"},{"others":[],"title":" I\u0027m not ready! ","url":"http://hydra-media.cursecdn.com/dota2.gamepedia.com/7/76/Slar_notyet_08.mp3"},{"others":[],"title":" It\u0027s not time yet! ","url":"http://hydra-media.cursecdn.com/dota2.gamepedia.com/2/27/Slar_notyet_09.mp3"},{"others":[],"title":" Out of mana. ","url":"http://hydra-media.cursecdn.com/dota2.gamepedia.com/9/9a/Slar_nomana_01.mp3"},{"others":[],"title":" No mana. ","url":"http://hydra-media.cursecdn.com/dota2.gamepedia.com/7/79/Slar_nomana_02.mp3"},{"others":[],"title":" Not enough mana. ","url":"http://hydra-media.cursecdn.com/dota2.gamepedia.com/6/63/Slar_nomana_03.mp3"},{"others":[],"title":" Out of mana. ","url":"http://hydra-media.cursecdn.com/dota2.gamepedia.com/e/e9/Slar_nomana_04.mp3"},{"others":[],"title":" No mana. ","url":"http://hydra-media.cursecdn.com/dota2.gamepedia.com/8/8c/Slar_nomana_05.mp3"},{"others":[],"title":" Not enough mana. ","url":"http://hydra-media.cursecdn.com/dota2.gamepedia.com/1/13/Slar_nomana_06.mp3"},{"others":[],"title":" Out of mana! ","url":"http://hydra-media.cursecdn.com/dota2.gamepedia.com/b/b7/Slar_nomana_07.mp3"},{"others":[],"title":" No mana! ","url":"http://hydra-media.cursecdn.com/dota2.gamepedia.com/5/55/Slar_nomana_08.mp3"},{"others":[],"title":" Not enough mana. ","url":"http://hydra-media.cursecdn.com/dota2.gamepedia.com/b/b3/Slar_nomana_09.mp3"},{"others":[],"title":" My deepest thanks. ","url":"http://hydra-media.cursecdn.com/dota2.gamepedia.com/3/3f/Slar_thanks_01.mp3"},{"others":[],"title":" The deep ones thank you. ","url":"http://hydra-media.cursecdn.com/dota2.gamepedia.com/9/96/Slar_thanks_02.mp3"},{"others":[],"title":" Thank you. ","url":"http://hydra-media.cursecdn.com/dota2.gamepedia.com/8/80/Slar_thanks_03.mp3"},{"others":[],"title":" I\u0027m under attack! ","url":"http://hydra-media.cursecdn.com/dota2.gamepedia.com/2/2b/Slar_underattack_01.mp3"},{"others":[],"title":" Eh heh it\u0027s in the bag. ","url":"http://hydra-media.cursecdn.com/dota2.gamepedia.com/a/a7/Slar_inthebag_01.mp3"},{"others":[],"title":" Buh, shitty wizard! ","url":"http://hydra-media.cursecdn.com/dota2.gamepedia.com/9/99/Slar_shitwiz_01.mp3"},{"others":[],"title":" Aheh, crummy wizard! ","url":"http://hydra-media.cursecdn.com/dota2.gamepedia.com/1/16/Slar_crumwiz_01.mp3"},{"others":[],"title":" Ugh. ","url":"http://hydra-media.cursecdn.com/dota2.gamepedia.com/1/13/Slar_pain_01.mp3"},{"others":[],"title":" Hell. ","url":"http://hydra-media.cursecdn.com/dota2.gamepedia.com/2/27/Slar_pain_02.mp3"},{"others":[],"title":" Ohh. ","url":"http://hydra-media.cursecdn.com/dota2.gamepedia.com/f/f9/Slar_pain_03.mp3"},{"others":[],"title":" Eshh. ","url":"http://hydra-media.cursecdn.com/dota2.gamepedia.com/7/74/Slar_pain_04.mp3"},{"others":[],"title":" Whooo. ","url":"http://hydra-media.cursecdn.com/dota2.gamepedia.com/6/67/Slar_pain_05.mp3"},{"others":[],"title":" Emm. ","url":"http://hydra-media.cursecdn.com/dota2.gamepedia.com/e/ec/Slar_pain_06.mp3"},{"others":[],"title":" Ommm. ","url":"http://hydra-media.cursecdn.com/dota2.gamepedia.com/c/c0/Slar_pain_07.mp3"},{"others":[],"title":" Oww. ","url":"http://hydra-media.cursecdn.com/dota2.gamepedia.com/3/33/Slar_pain_08.mp3"},{"others":[],"title":" Ewww. ","url":"http://hydra-media.cursecdn.com/dota2.gamepedia.com/b/bd/Slar_pain_09.mp3"},{"others":[],"title":" Owww. ","url":"http://hydra-media.cursecdn.com/dota2.gamepedia.com/e/ee/Slar_pain_10.mp3"},{"others":[],"title":" Oof. ","url":"http://hydra-media.cursecdn.com/dota2.gamepedia.com/6/60/Slar_pain_11.mp3"},{"others":[],"title":" Ahhh! ","url":"http://hydra-media.cursecdn.com/dota2.gamepedia.com/a/ac/Slar_pain_12.mp3"},{"others":[],"title":" Nowenar. ","url":"http://hydra-media.cursecdn.com/dota2.gamepedia.com/4/4c/Slar_anger_01.mp3"},{"others":[],"title":" Shiszar. ","url":"http://hydra-media.cursecdn.com/dota2.gamepedia.com/3/3c/Slar_anger_02.mp3"},{"others":[],"title":" Heeyez. ","url":"http://hydra-media.cursecdn.com/dota2.gamepedia.com/4/48/Slar_anger_03.mp3"},{"others":[],"title":" Heh. ","url":"http://hydra-media.cursecdn.com/dota2.gamepedia.com/b/b7/Slar_anger_04.mp3"},{"others":[],"title":" Hezaaah. ","url":"http://hydra-media.cursecdn.com/dota2.gamepedia.com/9/9d/Slar_anger_05.mp3"},{"others":[],"title":" Hiyeeze. ","url":"http://hydra-media.cursecdn.com/dota2.gamepedia.com/7/71/Slar_anger_06.mp3"},{"others":[],"title":" Heearah. ","url":"http://hydra-media.cursecdn.com/dota2.gamepedia.com/1/1b/Slar_happy_01.mp3"},{"others":[],"title":" Howashseseh. ","url":"http://hydra-media.cursecdn.com/dota2.gamepedia.com/1/1f/Slar_happy_02.mp3"},{"others":[],"title":" Heaaha. ","url":"http://hydra-media.cursecdn.com/dota2.gamepedia.com/b/b1/Slar_happy_03.mp3"},{"others":[],"title":" Mmmmem. ","url":"http://hydra-media.cursecdn.com/dota2.gamepedia.com/5/57/Slar_happy_04.mp3"},{"others":[],"title":" He he he he he. ","url":"http://hydra-media.cursecdn.com/dota2.gamepedia.com/c/c6/Slar_laugh_01.mp3"},{"others":[],"title":" He he ha he hah he heh heh. ","url":"http://hydra-media.cursecdn.com/dota2.gamepedia.com/d/de/Slar_laugh_02.mp3"},{"others":[],"title":" Tsee he he heh heh he heeh heh. ","url":"http://hydra-media.cursecdn.com/dota2.gamepedia.com/1/1c/Slar_laugh_03.mp3"},{"others":[],"title":" Ho ha ha ha hah heh heh. ","url":"http://hydra-media.cursecdn.com/dota2.gamepedia.com/0/05/Slar_laugh_04.mp3"},{"others":[],"title":" Tcheheheheh he he heh. ","url":"http://hydra-media.cursecdn.com/dota2.gamepedia.com/5/59/Slar_laugh_06.mp3"},{"others":[],"title":" Heh ehh heh eheh heh he heh. ","url":"http://hydra-media.cursecdn.com/dota2.gamepedia.com/3/31/Slar_laugh_07.mp3"},{"others":[],"title":" He hehheheeheheheheh. ","url":"http://hydra-media.cursecdn.com/dota2.gamepedia.com/5/58/Slar_laugh_08.mp3"},{"others":[],"title":" Hehheh eheah heah eeh. ","url":"http://hydra-media.cursecdn.com/dota2.gamepedia.com/6/6e/Slar_laugh_09.mp3"},{"others":[],"title":" Heah heh heh ehaheh. ","url":"http://hydra-media.cursecdn.com/dota2.gamepedia.com/a/a2/Slar_laugh_10.mp3"},{"others":[],"title":" Heeheheh hehe hah. ","url":"http://hydra-media.cursecdn.com/dota2.gamepedia.com/3/36/Slar_laugh_11.mp3"}]}