{"attrib": "+ 250 Health<br/>+ 6 HP Regeneration<br/>BLOCK CHANCE: 80%<br/>RANGED BLOCK: 20<br/>MELEE BLOCK: 40", "cd": false, "components": ["ring_of_health", "vitality_booster", "stout_shield"], "qual": "epic", "notes": "Multiple sources of damage block don\u0027t stack.", "desc": "Passive: Damage Block - Gives a chance to block damage, depending on the type of hero you are.", "dname": "Vanguard", "dotaId": "vanguard", "mc": false, "img": "vanguard_lg.png", "lore": "A powerful shield that defends its wielder from even the most vicious of attacks.", "id": 125, "created": true, "cost": 2225}