{"responses":[{"others":[],"title":" Queendom come! ","url":"http://hydra-media.cursecdn.com/dota2.gamepedia.com/0/0f/Pain_spawn_01.mp3"},{"others":[],"title":" There will be pain, there will be screaming. ","url":"http://hydra-media.cursecdn.com/dota2.gamepedia.com/9/91/Pain_spawn_02.mp3"},{"others":[],"title":" So begins the reign of pain. ","url":"http://hydra-media.cursecdn.com/dota2.gamepedia.com/b/b3/Pain_spawn_03.mp3"},{"others":[],"title":" Queen of Pain. ","url":"http://hydra-media.cursecdn.com/dota2.gamepedia.com/f/f9/Pain_spawn_04.mp3"},{"others":[],"title":" Make way for your Queen. ","url":"http://hydra-media.cursecdn.com/dota2.gamepedia.com/3/3a/Pain_begin_01.mp3"},{"others":[],"title":" Heh, he he he he he he he. ","url":"http://hydra-media.cursecdn.com/dota2.gamepedia.com/d/d5/Pain_first_01.mp3"},{"others":[],"title":" First blood! Just a little, he he he. ","url":"http://hydra-media.cursecdn.com/dota2.gamepedia.com/2/29/Pain_first_02.mp3"},{"others":[],"title":" Oh yes! ","url":"http://hydra-media.cursecdn.com/dota2.gamepedia.com/4/4b/Pain_move_01.mp3"},{"others":[],"title":" Oh yes. ","url":"http://hydra-media.cursecdn.com/dota2.gamepedia.com/c/c4/Pain_move_02.mp3"},{"others":[],"title":" Your Queen moves. ","url":"http://hydra-media.cursecdn.com/dota2.gamepedia.com/6/6c/Pain_move_03.mp3"},{"others":[],"title":" A royal path! ","url":"http://hydra-media.cursecdn.com/dota2.gamepedia.com/3/38/Pain_move_04.mp3"},{"others":[],"title":" Forward. ","url":"http://hydra-media.cursecdn.com/dota2.gamepedia.com/b/bc/Pain_move_05.mp3"},{"others":[],"title":" A path to pain. ","url":"http://hydra-media.cursecdn.com/dota2.gamepedia.com/6/61/Pain_move_06.mp3"},{"others":[],"title":" Forward. ","url":"http://hydra-media.cursecdn.com/dota2.gamepedia.com/4/40/Pain_move_07.mp3"},{"others":[],"title":" The pain train. ","url":"http://hydra-media.cursecdn.com/dota2.gamepedia.com/c/c0/Pain_move_08.mp3"},{"others":[],"title":" Here here! ","url":"http://hydra-media.cursecdn.com/dota2.gamepedia.com/2/29/Pain_move_09.mp3"},{"others":[],"title":" Swiftly. ","url":"http://hydra-media.cursecdn.com/dota2.gamepedia.com/b/b3/Pain_move_10.mp3"},{"others":[],"title":" As I will. ","url":"http://hydra-media.cursecdn.com/dota2.gamepedia.com/d/dd/Pain_move_11.mp3"},{"others":[],"title":" Quickly now. ","url":"http://hydra-media.cursecdn.com/dota2.gamepedia.com/a/ae/Pain_move_12.mp3"},{"others":[],"title":" Oh yes! ","url":"http://hydra-media.cursecdn.com/dota2.gamepedia.com/0/0f/Pain_move_13.mp3"},{"others":[],"title":" Attack! ","url":"http://hydra-media.cursecdn.com/dota2.gamepedia.com/6/61/Pain_attack_01.mp3"},{"others":[],"title":" Reign of pain! ","url":"http://hydra-media.cursecdn.com/dota2.gamepedia.com/a/a9/Pain_attack_02.mp3"},{"others":[],"title":" Share my pain! ","url":"http://hydra-media.cursecdn.com/dota2.gamepedia.com/f/ff/Pain_attack_03.mp3"},{"others":[],"title":" Does this hurt? ","url":"http://hydra-media.cursecdn.com/dota2.gamepedia.com/8/89/Pain_attack_04.mp3"},{"others":[],"title":" A love bite! ","url":"http://hydra-media.cursecdn.com/dota2.gamepedia.com/f/f4/Pain_attack_05.mp3"},{"others":[],"title":" Feel this! ","url":"http://hydra-media.cursecdn.com/dota2.gamepedia.com/a/ad/Pain_attack_06.mp3"},{"others":[],"title":" Suffer! ","url":"http://hydra-media.cursecdn.com/dota2.gamepedia.com/5/59/Pain_attack_07.mp3"},{"others":[],"title":" Sweet pain. ","url":"http://hydra-media.cursecdn.com/dota2.gamepedia.com/a/aa/Pain_attack_08.mp3"},{"others":[],"title":" Scream! ","url":"http://hydra-media.cursecdn.com/dota2.gamepedia.com/2/25/Pain_attack_09.mp3"},{"others":[],"title":" Pain builds character. ","url":"http://hydra-media.cursecdn.com/dota2.gamepedia.com/e/e4/Pain_attack_10.mp3"},{"others":[],"title":" Submit. ","url":"http://hydra-media.cursecdn.com/dota2.gamepedia.com/a/a9/Pain_attack_11.mp3"},{"others":[],"title":" I love a struggle. ","url":"http://hydra-media.cursecdn.com/dota2.gamepedia.com/2/2f/Pain_attack_12.mp3"},{"others":[],"title":" I love it when you resist. ","url":"http://hydra-media.cursecdn.com/dota2.gamepedia.com/9/9c/Pain_cast_01.mp3"},{"others":[],"title":" You\u0027ve got it coming. ","url":"http://hydra-media.cursecdn.com/dota2.gamepedia.com/6/63/Pain_cast_02.mp3"},{"others":[],"title":" Agony awaits! ","url":"http://hydra-media.cursecdn.com/dota2.gamepedia.com/3/38/Pain_cast_03.mp3"},{"others":[],"title":" Poison dagger! ","url":"http://hydra-media.cursecdn.com/dota2.gamepedia.com/6/61/Pain_ability_shadowstrike_01.mp3"},{"others":[],"title":" A little knife play? ","url":"http://hydra-media.cursecdn.com/dota2.gamepedia.com/0/09/Pain_ability_shadowstrike_02.mp3"},{"others":[],"title":" You\u0027ll like your new piercing. ","url":"http://hydra-media.cursecdn.com/dota2.gamepedia.com/8/8d/Pain_ability_shadowstrike_03.mp3"},{"others":[],"title":" Oh! I love your new piercing! ","url":"http://hydra-media.cursecdn.com/dota2.gamepedia.com/c/c0/Pain_ability_shadowstrike_04.mp3"},{"others":[],"title":" Was it really that bad? ","url":"http://hydra-media.cursecdn.com/dota2.gamepedia.com/b/b8/Pain_ability_screamofpain_01.mp3"},{"others":[],"title":" You were weak. ","url":"http://hydra-media.cursecdn.com/dota2.gamepedia.com/5/55/Pain_ability_screamofpain_02.mp3"},{"others":[],"title":" Death comes in at the ears. ","url":"http://hydra-media.cursecdn.com/dota2.gamepedia.com/8/85/Pain_ability_screamofpain_03.mp3"},{"others":[],"title":" Didn\u0027t like the sound of that? ","url":"http://hydra-media.cursecdn.com/dota2.gamepedia.com/6/6f/Pain_ability_screamofpain_04.mp3"},{"others":[],"title":" Ah he he he he he, that was the sound of your death. ","url":"http://hydra-media.cursecdn.com/dota2.gamepedia.com/4/43/Pain_ability_sonicwave_01.mp3"},{"others":[],"title":" The last sound you\u0027ll hear. ","url":"http://hydra-media.cursecdn.com/dota2.gamepedia.com/f/f7/Pain_ability_sonicwave_02.mp3"},{"others":[],"title":" ah ha ha ha, let the waves of pain carry you off. ","url":"http://hydra-media.cursecdn.com/dota2.gamepedia.com/b/b5/Pain_ability_sonicwave_03.mp3"},{"others":[],"title":" Death travels faster than sound. ","url":"http://hydra-media.cursecdn.com/dota2.gamepedia.com/6/61/Pain_ability_sonicwave_04.mp3"},{"others":[],"title":" Growing pains! ","url":"http://hydra-media.cursecdn.com/dota2.gamepedia.com/d/d4/Pain_levelup_01.mp3"},{"others":[],"title":" No pain, no gain. ","url":"http://hydra-media.cursecdn.com/dota2.gamepedia.com/6/6b/Pain_levelup_02.mp3"},{"others":[],"title":" Queen me! ","url":"http://hydra-media.cursecdn.com/dota2.gamepedia.com/a/a9/Pain_levelup_03.mp3"},{"others":[],"title":" Ooh! I felt that! ","url":"http://hydra-media.cursecdn.com/dota2.gamepedia.com/d/d9/Pain_levelup_04.mp3"},{"others":[],"title":" Growing stronger! ","url":"http://hydra-media.cursecdn.com/dota2.gamepedia.com/a/a5/Pain_levelup_05.mp3"},{"others":[],"title":" More, more! ","url":"http://hydra-media.cursecdn.com/dota2.gamepedia.com/c/c0/Pain_levelup_06.mp3"},{"others":[],"title":" My pain tolerance increases. ","url":"http://hydra-media.cursecdn.com/dota2.gamepedia.com/3/38/Pain_levelup_07.mp3"},{"others":[],"title":" My bindings tighten! ","url":"http://hydra-media.cursecdn.com/dota2.gamepedia.com/c/c3/Pain_levelup_08.mp3"},{"others":[],"title":" mu ha ha ha ha ha ha ha ha ha ha ha ha ","url":"http://hydra-media.cursecdn.com/dota2.gamepedia.com/f/ff/Pain_levelup_09.mp3"},{"others":[],"title":" oh ha ha ha ha ha ha ","url":"http://hydra-media.cursecdn.com/dota2.gamepedia.com/b/b0/Pain_levelup_10.mp3"},{"others":[],"title":" oh ha ha ha ha ha ha ha ha ha ha ha ha ","url":"http://hydra-media.cursecdn.com/dota2.gamepedia.com/c/cb/Pain_levelup_11.mp3"},{"others":[],"title":" The last sound you\u0027ll ever hear. ","url":"http://hydra-media.cursecdn.com/dota2.gamepedia.com/7/7b/Pain_kill_01.mp3"},{"others":[],"title":" I do suffer fools. ","url":"http://hydra-media.cursecdn.com/dota2.gamepedia.com/4/47/Pain_kill_02.mp3"},{"others":[],"title":" I\u0027m a pain specialist. ","url":"http://hydra-media.cursecdn.com/dota2.gamepedia.com/c/c2/Pain_kill_03.mp3"},{"others":[],"title":" Pain is the best teacher. ","url":"http://hydra-media.cursecdn.com/dota2.gamepedia.com/7/74/Pain_kill_04.mp3"},{"others":[],"title":" Did you forget your safe word? ","url":"http://hydra-media.cursecdn.com/dota2.gamepedia.com/b/bd/Pain_kill_05.mp3"},{"others":[],"title":" I scream bloody murder. ","url":"http://hydra-media.cursecdn.com/dota2.gamepedia.com/f/fc/Pain_kill_06.mp3"},{"others":[],"title":" The ecstasy of agony. ","url":"http://hydra-media.cursecdn.com/dota2.gamepedia.com/f/f0/Pain_kill_07.mp3"},{"others":[],"title":" You hurt the ones you love. ","url":"http://hydra-media.cursecdn.com/dota2.gamepedia.com/a/ae/Pain_kill_08.mp3"},{"others":[],"title":" Exquisite agony. ","url":"http://hydra-media.cursecdn.com/dota2.gamepedia.com/c/c0/Pain_kill_09.mp3"},{"others":[],"title":" ohh, such a little death. ","url":"http://hydra-media.cursecdn.com/dota2.gamepedia.com/b/b1/Pain_kill_10.mp3"},{"others":[],"title":" Sound of mind and body. ","url":"http://hydra-media.cursecdn.com/dota2.gamepedia.com/3/33/Pain_kill_11.mp3"},{"others":[],"title":" That was perfect. ","url":"http://hydra-media.cursecdn.com/dota2.gamepedia.com/4/4a/Pain_kill_12.mp3"},{"others":[],"title":" I\u0027m sorry, did you say stop? ","url":"http://hydra-media.cursecdn.com/dota2.gamepedia.com/2/28/Pain_kill_13.mp3"},{"others":[],"title":" mu ha ha ha ha ha ha ha ha ha ha ha ","url":"http://hydra-media.cursecdn.com/dota2.gamepedia.com/8/82/Pain_kill_14.mp3"},{"others":[],"title":" oh, ha ha ha ha ha ha ha ha ha ha ","url":"http://hydra-media.cursecdn.com/dota2.gamepedia.com/6/62/Pain_kill_15.mp3"},{"others":[],"title":" ah he he he he he. ","url":"http://hydra-media.cursecdn.com/dota2.gamepedia.com/0/06/Pain_kill_16.mp3"},{"others":["night_stalker"],"title":" Night Stalker, you aren\u0027t the only thing that goes bump in the night. ","url":"http://hydra-media.cursecdn.com/dota2.gamepedia.com/0/01/Pain_rival_01.mp3"},{"others":["night_stalker"],"title":" Night Stalker, you\u0027re only a little pain. ","url":"http://hydra-media.cursecdn.com/dota2.gamepedia.com/3/38/Pain_rival_02.mp3"},{"others":["antimage"],"title":" Maybe now you\u0027ll stop blinking around, Anti-Mage? ","url":"http://hydra-media.cursecdn.com/dota2.gamepedia.com/e/e6/Pain_rival_03.mp3"},{"others":["antimage"],"title":" Oh, Anti-Mage, I\u0027ll make you break your vows. ","url":"http://hydra-media.cursecdn.com/dota2.gamepedia.com/3/38/Pain_rival_04.mp3"},{"others":["antimage"],"title":" It\u0027s all about discipline, Anti-Mage. ","url":"http://hydra-media.cursecdn.com/dota2.gamepedia.com/a/ad/Pain_rival_05.mp3"},{"others":["enchantress"],"title":" Enchantress, such an innocent creature. ","url":"http://hydra-media.cursecdn.com/dota2.gamepedia.com/0/01/Pain_rival_06.mp3"},{"others":["enchantress"],"title":" Enchantress, how little you know, you poor plain thing. ","url":"http://hydra-media.cursecdn.com/dota2.gamepedia.com/d/d5/Pain_rival_07.mp3"},{"others":["enchantress"],"title":" Oh, Enchantress, what I could do with those hooves. ","url":"http://hydra-media.cursecdn.com/dota2.gamepedia.com/a/ae/Pain_rival_08.mp3"},{"others":["enchantress"],"title":" Didn\u0027t know you could be broken, Enchantress. ","url":"http://hydra-media.cursecdn.com/dota2.gamepedia.com/5/51/Pain_rival_09.mp3"},{"others":["crystal_maiden"],"title":" Crystal Maiden... are you really, I wonder? ","url":"http://hydra-media.cursecdn.com/dota2.gamepedia.com/d/d3/Pain_rival_10.mp3"},{"others":["silencer"],"title":" Silencer? I\u0027d prefer a screamer. ","url":"http://hydra-media.cursecdn.com/dota2.gamepedia.com/2/2b/Pain_rival_11.mp3"},{"others":["skeleton_king"],"title":" King for a day… Queen for eternity. ","url":"http://hydra-media.cursecdn.com/dota2.gamepedia.com/1/12/Pain_rival_13.mp3"},{"others":["clinkz"],"title":" Bones and no flesh? Where\u0027s the pleasure in that? ","url":"http://hydra-media.cursecdn.com/dota2.gamepedia.com/8/83/Pain_rival_14.mp3"},{"others":["clinkz"],"title":" I like them with a little more meat on their bones. ","url":"http://hydra-media.cursecdn.com/dota2.gamepedia.com/0/02/Pain_rival_15.mp3"},{"others":["legion_commander"],"title":" That\u0027s why I\u0027m queen, and you\u0027re nothing. ","url":"http://hydra-media.cursecdn.com/dota2.gamepedia.com/1/14/Pain_specialcase_01.mp3"},{"others":["templar_assassin","windrunner"],"title":" Submit to your lady, little girl. ","url":"http://hydra-media.cursecdn.com/dota2.gamepedia.com/a/a1/Pain_specialcase_03.mp3"},{"others":["antimage","riki","phantom_assassin"],"title":" Blink! You\u0027re dead. ","url":"http://hydra-media.cursecdn.com/dota2.gamepedia.com/1/19/Pain_specialcase_04.mp3"},{"others":["riki","broodmother","nyx_assassin","weaver","bounty_hunter"],"title":" Oh! I almost missed you. ","url":"http://hydra-media.cursecdn.com/dota2.gamepedia.com/6/67/Pain_specialcase_06.mp3"},{"others":["omniknight"],"title":" You want me? Come get me. ","url":"http://hydra-media.cursecdn.com/dota2.gamepedia.com/9/9b/Pain_taunt_01.mp3"},{"others":["undying","life_stealer","medusa"],"title":" You can look but don\u0027t touch. Come to think of it, don\u0027t look either. ","url":"http://hydra-media.cursecdn.com/dota2.gamepedia.com/b/b4/Pain_taunt_04.mp3"},{"others":[],"title":" For the royal coffers. ","url":"http://hydra-media.cursecdn.com/dota2.gamepedia.com/3/3e/Pain_lasthit_01.mp3"},{"others":[],"title":" The treasury grows. ","url":"http://hydra-media.cursecdn.com/dota2.gamepedia.com/d/db/Pain_lasthit_02.mp3"},{"others":[],"title":" Worthy tribute. ","url":"http://hydra-media.cursecdn.com/dota2.gamepedia.com/5/5e/Pain_lasthit_03.mp3"},{"others":[],"title":" Your pain ends. ","url":"http://hydra-media.cursecdn.com/dota2.gamepedia.com/b/be/Pain_lasthit_04.mp3"},{"others":[],"title":" Your pain, my gain. ","url":"http://hydra-media.cursecdn.com/dota2.gamepedia.com/6/6a/Pain_lasthit_05.mp3"},{"others":[],"title":" Pay for the privilege. ","url":"http://hydra-media.cursecdn.com/dota2.gamepedia.com/7/7c/Pain_lasthit_06.mp3"},{"others":[],"title":" Oh, royalties! ","url":"http://hydra-media.cursecdn.com/dota2.gamepedia.com/2/29/Pain_lasthit_07.mp3"},{"others":[],"title":" Gold for my crown. ","url":"http://hydra-media.cursecdn.com/dota2.gamepedia.com/b/b4/Pain_lasthit_08.mp3"},{"others":[],"title":" Top is missing! ","url":"http://hydra-media.cursecdn.com/dota2.gamepedia.com/b/b4/Pain_missing_lane_01.mp3"},{"others":[],"title":" Middle is missing! ","url":"http://hydra-media.cursecdn.com/dota2.gamepedia.com/c/c4/Pain_missing_lane_02.mp3"},{"others":[],"title":" Bottom is missing! ","url":"http://hydra-media.cursecdn.com/dota2.gamepedia.com/3/36/Pain_missing_lane_03.mp3"},{"others":[],"title":" No! ","url":"http://hydra-media.cursecdn.com/dota2.gamepedia.com/d/d1/Pain_death_01.mp3"},{"others":[],"title":" No! ","url":"http://hydra-media.cursecdn.com/dota2.gamepedia.com/9/9b/Pain_death_02.mp3"},{"others":[],"title":" Our roleplay, ends. ","url":"http://hydra-media.cursecdn.com/dota2.gamepedia.com/b/b1/Pain_death_03.mp3"},{"others":[],"title":" Losing my voice. ","url":"http://hydra-media.cursecdn.com/dota2.gamepedia.com/f/f9/Pain_death_04.mp3"},{"others":[],"title":" Under pain of death. ","url":"http://hydra-media.cursecdn.com/dota2.gamepedia.com/7/73/Pain_death_05.mp3"},{"others":[],"title":" Bury me in the royal catacombs. ","url":"http://hydra-media.cursecdn.com/dota2.gamepedia.com/6/6a/Pain_death_06.mp3"},{"others":[],"title":" I felt that! ","url":"http://hydra-media.cursecdn.com/dota2.gamepedia.com/b/b1/Pain_death_07.mp3"},{"others":[],"title":" I leave this world of hurt. ","url":"http://hydra-media.cursecdn.com/dota2.gamepedia.com/a/a5/Pain_death_08.mp3"},{"others":[],"title":" Oh! That hardly hurt at all. ","url":"http://hydra-media.cursecdn.com/dota2.gamepedia.com/5/56/Pain_death_09.mp3"},{"others":[],"title":" I declare a month of mourning. ","url":"http://hydra-media.cursecdn.com/dota2.gamepedia.com/9/9d/Pain_death_10.mp3"},{"others":[],"title":" What a pain in the aaaaaaaaaa! ","url":"http://hydra-media.cursecdn.com/dota2.gamepedia.com/2/28/Pain_death_11.mp3"},{"others":[],"title":" I felt that! ","url":"http://hydra-media.cursecdn.com/dota2.gamepedia.com/f/fc/Pain_death_12.mp3"},{"others":[],"title":" Your queen is dead. ","url":"http://hydra-media.cursecdn.com/dota2.gamepedia.com/0/00/Pain_death_13.mp3"},{"others":[],"title":" No! ","url":"http://hydra-media.cursecdn.com/dota2.gamepedia.com/1/1c/Pain_death_14.mp3"},{"others":[],"title":" I\u0027ll be my own successor! ","url":"http://hydra-media.cursecdn.com/dota2.gamepedia.com/9/9b/Pain_fastres_01.mp3"},{"others":[],"title":" Long live your Queen! ","url":"http://hydra-media.cursecdn.com/dota2.gamepedia.com/2/21/Pain_respawn_01.mp3"},{"others":[],"title":" My voice returns! ","url":"http://hydra-media.cursecdn.com/dota2.gamepedia.com/1/1d/Pain_respawn_02.mp3"},{"others":[],"title":" Play it again. ","url":"http://hydra-media.cursecdn.com/dota2.gamepedia.com/9/9f/Pain_respawn_03.mp3"},{"others":[],"title":" I know I\u0027m a pain, but you love me anyway. ","url":"http://hydra-media.cursecdn.com/dota2.gamepedia.com/4/4c/Pain_respawn_04.mp3"},{"others":[],"title":" I\u0027m feeling no pain. ","url":"http://hydra-media.cursecdn.com/dota2.gamepedia.com/0/02/Pain_respawn_05.mp3"},{"others":[],"title":" The Queen is dead, long live the Queen. ","url":"http://hydra-media.cursecdn.com/dota2.gamepedia.com/3/35/Pain_respawn_06.mp3"},{"others":[],"title":" I guess the crown passes to me. ","url":"http://hydra-media.cursecdn.com/dota2.gamepedia.com/5/5a/Pain_respawn_07.mp3"},{"others":[],"title":" Bringing the pain! ","url":"http://hydra-media.cursecdn.com/dota2.gamepedia.com/f/f4/Pain_respawn_08.mp3"},{"others":[],"title":" A royal return. ","url":"http://hydra-media.cursecdn.com/dota2.gamepedia.com/8/87/Pain_respawn_09.mp3"},{"others":[],"title":" I\u0027m in a world of pain, it\u0027s wonderful! ","url":"http://hydra-media.cursecdn.com/dota2.gamepedia.com/d/df/Pain_respawn_10.mp3"},{"others":[],"title":" Time for some roleplay. ","url":"http://hydra-media.cursecdn.com/dota2.gamepedia.com/6/64/Pain_rare_01.mp3"},{"others":[],"title":" The forecast calls for pain like rain, and it\u0027s monsoon season. ","url":"http://hydra-media.cursecdn.com/dota2.gamepedia.com/9/90/Pain_rare_02.mp3"},{"others":[],"title":" They say pain is all in the mind, but they\u0027re wrong: It\u0027s all in my hands. ","url":"http://hydra-media.cursecdn.com/dota2.gamepedia.com/b/b6/Pain_rare_03.mp3"},{"others":[],"title":" Yes, I am a trauma Queen. ","url":"http://hydra-media.cursecdn.com/dota2.gamepedia.com/3/3c/Pain_rare_04.mp3"},{"others":[],"title":" You\u0027ll find that I\u0027m all stick and no carrot. ","url":"http://hydra-media.cursecdn.com/dota2.gamepedia.com/d/dc/Pain_rare_05.mp3"},{"others":[],"title":" You always hurt the ones you love, also the ones you hate. ","url":"http://hydra-media.cursecdn.com/dota2.gamepedia.com/6/6b/Pain_rare_06.mp3"},{"others":[],"title":" Bought for a song! ","url":"http://hydra-media.cursecdn.com/dota2.gamepedia.com/c/cd/Pain_purch_01.mp3"},{"others":[],"title":" It pains my pocketbook. ","url":"http://hydra-media.cursecdn.com/dota2.gamepedia.com/1/1b/Pain_purch_02.mp3"},{"others":[],"title":" Fit for a Queen. ","url":"http://hydra-media.cursecdn.com/dota2.gamepedia.com/1/1c/Pain_purch_03.mp3"},{"others":[],"title":" Bottle royale. ","url":"http://hydra-media.cursecdn.com/dota2.gamepedia.com/a/a6/Pain_bottle_01.mp3"},{"others":[],"title":" Something for the pain. ","url":"http://hydra-media.cursecdn.com/dota2.gamepedia.com/8/87/Pain_bottle_02.mp3"},{"others":[],"title":" Into the bottle. ","url":"http://hydra-media.cursecdn.com/dota2.gamepedia.com/e/e5/Pain_bottle_03.mp3"},{"others":[],"title":" Blink dagger? That was quite unnecessary. ","url":"http://hydra-media.cursecdn.com/dota2.gamepedia.com/a/af/Pain_blink_01.mp3"},{"others":[],"title":" What need have I for this? ","url":"http://hydra-media.cursecdn.com/dota2.gamepedia.com/1/12/Pain_blink_02.mp3"},{"others":[],"title":" A scepter for the Queen! ","url":"http://hydra-media.cursecdn.com/dota2.gamepedia.com/9/97/Pain_scepter_01.mp3"},{"others":[],"title":" So much sweeter with scepter! ","url":"http://hydra-media.cursecdn.com/dota2.gamepedia.com/1/1f/Pain_scepter_02.mp3"},{"others":[],"title":" Scepter shock! ","url":"http://hydra-media.cursecdn.com/dota2.gamepedia.com/7/7a/Pain_scepter_03.mp3"},{"others":[],"title":" Sonic scepter! ","url":"http://hydra-media.cursecdn.com/dota2.gamepedia.com/d/d4/Pain_scepter_04.mp3"},{"others":[],"title":" Scythe of Vyse. ","url":"http://hydra-media.cursecdn.com/dota2.gamepedia.com/f/fd/Pain_relic_01.mp3"},{"others":[],"title":" Linkens Sphere! ","url":"http://hydra-media.cursecdn.com/dota2.gamepedia.com/b/b0/Pain_relic_02.mp3"},{"others":[],"title":" Skadi! ","url":"http://hydra-media.cursecdn.com/dota2.gamepedia.com/8/80/Pain_relic_03.mp3"},{"others":[],"title":" Denied. ","url":"http://hydra-media.cursecdn.com/dota2.gamepedia.com/c/ca/Pain_deny_01.mp3"},{"others":[],"title":" Denied. ","url":"http://hydra-media.cursecdn.com/dota2.gamepedia.com/d/d4/Pain_deny_02.mp3"},{"others":[],"title":" No! ","url":"http://hydra-media.cursecdn.com/dota2.gamepedia.com/3/31/Pain_deny_03.mp3"},{"others":[],"title":" You\u0027re simply not worthy. ","url":"http://hydra-media.cursecdn.com/dota2.gamepedia.com/4/4d/Pain_deny_04.mp3"},{"others":[],"title":" Oh, did that hurt? ","url":"http://hydra-media.cursecdn.com/dota2.gamepedia.com/8/8b/Pain_deny_05.mp3"},{"others":[],"title":" Thought you had that, didn\u0027t you? ","url":"http://hydra-media.cursecdn.com/dota2.gamepedia.com/7/7d/Pain_deny_06.mp3"},{"others":[],"title":" Ah, no gold for you! ","url":"http://hydra-media.cursecdn.com/dota2.gamepedia.com/6/63/Pain_deny_07.mp3"},{"others":[],"title":" uh uh uh. ","url":"http://hydra-media.cursecdn.com/dota2.gamepedia.com/1/17/Pain_deny_08.mp3"},{"others":[],"title":" Too bad. ","url":"http://hydra-media.cursecdn.com/dota2.gamepedia.com/0/07/Pain_deny_09.mp3"},{"others":[],"title":" Too bad! ","url":"http://hydra-media.cursecdn.com/dota2.gamepedia.com/1/1f/Pain_deny_10.mp3"},{"others":[],"title":" ah ha ha ha ha ha ha ha ha ha ha ha. ","url":"http://hydra-media.cursecdn.com/dota2.gamepedia.com/a/aa/Pain_deny_11.mp3"},{"others":[],"title":" ah ha ha ha ha ha ha ha ha ha ha ha. ","url":"http://hydra-media.cursecdn.com/dota2.gamepedia.com/c/cf/Pain_deny_12.mp3"},{"others":[],"title":" uhuh. ","url":"http://hydra-media.cursecdn.com/dota2.gamepedia.com/a/af/Pain_deny_13.mp3"},{"others":[],"title":" ah ha ha ha. ","url":"http://hydra-media.cursecdn.com/dota2.gamepedia.com/d/d3/Pain_deny_14.mp3"},{"others":[],"title":" ah ha ha ha. ","url":"http://hydra-media.cursecdn.com/dota2.gamepedia.com/6/6f/Pain_deny_15.mp3"},{"others":[],"title":" Noooo! ","url":"http://hydra-media.cursecdn.com/dota2.gamepedia.com/4/4c/Pain_lose_01.mp3"},{"others":[],"title":" Noooo! ","url":"http://hydra-media.cursecdn.com/dota2.gamepedia.com/a/ac/Pain_lose_02.mp3"},{"others":[],"title":" Defeated! ","url":"http://hydra-media.cursecdn.com/dota2.gamepedia.com/9/91/Pain_lose_03.mp3"},{"others":[],"title":" You\u0027ll hear no more from me! ","url":"http://hydra-media.cursecdn.com/dota2.gamepedia.com/a/ac/Pain_lose_04.mp3"},{"others":[],"title":" Yes! ","url":"http://hydra-media.cursecdn.com/dota2.gamepedia.com/8/84/Pain_win_01.mp3"},{"others":[],"title":" Victory! ","url":"http://hydra-media.cursecdn.com/dota2.gamepedia.com/c/ca/Pain_win_02.mp3"},{"others":[],"title":" The pain shall set you free, ha ha ha ha ha ha ha ha ha ha ha ha ","url":"http://hydra-media.cursecdn.com/dota2.gamepedia.com/e/ed/Pain_win_03.mp3"},{"others":[],"title":" Immortality! ","url":"http://hydra-media.cursecdn.com/dota2.gamepedia.com/a/a2/Pain_immort_01.mp3"},{"others":[],"title":" My voice carries forever! ","url":"http://hydra-media.cursecdn.com/dota2.gamepedia.com/1/16/Pain_immort_02.mp3"},{"others":[],"title":" Haste! ","url":"http://hydra-media.cursecdn.com/dota2.gamepedia.com/c/c6/Pain_haste_01.mp3"},{"others":[],"title":" Twice the speed of sound! ","url":"http://hydra-media.cursecdn.com/dota2.gamepedia.com/d/d8/Pain_haste_02.mp3"},{"others":[],"title":" Double damage! ","url":"http://hydra-media.cursecdn.com/dota2.gamepedia.com/6/6e/Pain_doubdam_01.mp3"},{"others":[],"title":" I\u0027ll have them screaming duets! ","url":"http://hydra-media.cursecdn.com/dota2.gamepedia.com/c/cf/Pain_doubdam_02.mp3"},{"others":[],"title":" Regeneration! ","url":"http://hydra-media.cursecdn.com/dota2.gamepedia.com/1/12/Pain_regen_01.mp3"},{"others":[],"title":" Pain without consequence! ","url":"http://hydra-media.cursecdn.com/dota2.gamepedia.com/6/66/Pain_regen_02.mp3"},{"others":[],"title":" Illusion! ","url":"http://hydra-media.cursecdn.com/dota2.gamepedia.com/1/19/Pain_illus_01.mp3"},{"others":[],"title":" Misery loves company. ","url":"http://hydra-media.cursecdn.com/dota2.gamepedia.com/1/13/Pain_illus_02.mp3"},{"others":[],"title":" Invisibility! ","url":"http://hydra-media.cursecdn.com/dota2.gamepedia.com/7/75/Pain_invis_01.mp3"},{"others":[],"title":" What you don\u0027t see can most certainly hurt you. ","url":"http://hydra-media.cursecdn.com/dota2.gamepedia.com/7/7c/Pain_invis_02.mp3"},{"others":[],"title":" Worthy tribute. ","url":"http://hydra-media.cursecdn.com/dota2.gamepedia.com/5/5e/Pain_lasthit_03.mp3"},{"others":[],"title":" Not yet. ","url":"http://hydra-media.cursecdn.com/dota2.gamepedia.com/c/c5/Pain_notyet_01.mp3"},{"others":[],"title":" Not yet! ","url":"http://hydra-media.cursecdn.com/dota2.gamepedia.com/1/11/Pain_notyet_02.mp3"},{"others":[],"title":" Not yet! ","url":"http://hydra-media.cursecdn.com/dota2.gamepedia.com/9/92/Pain_notyet_03.mp3"},{"others":[],"title":" I\u0027m not ready. ","url":"http://hydra-media.cursecdn.com/dota2.gamepedia.com/0/03/Pain_notyet_04.mp3"},{"others":[],"title":" I\u0027m not ready! ","url":"http://hydra-media.cursecdn.com/dota2.gamepedia.com/6/6e/Pain_notyet_05.mp3"},{"others":[],"title":" I\u0027m not ready! ","url":"http://hydra-media.cursecdn.com/dota2.gamepedia.com/b/b8/Pain_notyet_06.mp3"},{"others":[],"title":" It\u0027s not time yet. ","url":"http://hydra-media.cursecdn.com/dota2.gamepedia.com/6/63/Pain_notyet_07.mp3"},{"others":[],"title":" It\u0027s not time yet! ","url":"http://hydra-media.cursecdn.com/dota2.gamepedia.com/8/8b/Pain_notyet_08.mp3"},{"others":[],"title":" It\u0027s not time yet! ","url":"http://hydra-media.cursecdn.com/dota2.gamepedia.com/4/4e/Pain_notyet_09.mp3"},{"others":[],"title":" Out of mana. ","url":"http://hydra-media.cursecdn.com/dota2.gamepedia.com/2/23/Pain_nomana_01.mp3"},{"others":[],"title":" Out of mana! ","url":"http://hydra-media.cursecdn.com/dota2.gamepedia.com/1/14/Pain_nomana_02.mp3"},{"others":[],"title":" Out of mana! ","url":"http://hydra-media.cursecdn.com/dota2.gamepedia.com/3/3e/Pain_nomana_03.mp3"},{"others":[],"title":" No mana. ","url":"http://hydra-media.cursecdn.com/dota2.gamepedia.com/6/6b/Pain_nomana_04.mp3"},{"others":[],"title":" No mana! ","url":"http://hydra-media.cursecdn.com/dota2.gamepedia.com/1/1e/Pain_nomana_05.mp3"},{"others":[],"title":" No mana! ","url":"http://hydra-media.cursecdn.com/dota2.gamepedia.com/0/0b/Pain_nomana_06.mp3"},{"others":[],"title":" Not enough mana. ","url":"http://hydra-media.cursecdn.com/dota2.gamepedia.com/1/14/Pain_nomana_07.mp3"},{"others":[],"title":" Not enough mana! ","url":"http://hydra-media.cursecdn.com/dota2.gamepedia.com/b/bd/Pain_nomana_08.mp3"},{"others":[],"title":" Not enough mana! ","url":"http://hydra-media.cursecdn.com/dota2.gamepedia.com/6/6a/Pain_nomana_09.mp3"},{"others":[],"title":" My thanks. ","url":"http://hydra-media.cursecdn.com/dota2.gamepedia.com/0/03/Pain_thanks_01.mp3"},{"others":[],"title":" I\u0027m ever so grateful. ","url":"http://hydra-media.cursecdn.com/dota2.gamepedia.com/6/67/Pain_thanks_02.mp3"},{"others":[],"title":" I\u0027m under attack! ","url":"http://hydra-media.cursecdn.com/dota2.gamepedia.com/a/a6/Pain_underattack_01.mp3"},{"others":[],"title":" This one is so in the bag! ","url":"http://hydra-media.cursecdn.com/dota2.gamepedia.com/b/b8/Pain_inthebag_01.mp3"},{"others":[],"title":" It feels so good to be bad. ","url":"http://hydra-media.cursecdn.com/dota2.gamepedia.com/4/48/Pain_taunt_02.mp3"},{"others":["abaddon"],"title":" ","url":"http://hydra-media.cursecdn.com/dota2.gamepedia.com/5/58/Pain_taunt_03.mp3"},{"others":["abaddon"],"title":" ","url":"http://hydra-media.cursecdn.com/dota2.gamepedia.com/a/ae/Pain_shiwiz_01.mp3"},{"others":[],"title":" Shitty wizard! ","url":"http://hydra-media.cursecdn.com/dota2.gamepedia.com/a/ae/Pain_shiwiz_01.mp3"},{"others":[],"title":" Crummy wizard! ","url":"http://hydra-media.cursecdn.com/dota2.gamepedia.com/0/03/Pain_crumwiz_01.mp3"},{"others":[],"title":" Uh! ","url":"http://hydra-media.cursecdn.com/dota2.gamepedia.com/4/46/Pain_pain_01.mp3"},{"others":[],"title":" Oh! ","url":"http://hydra-media.cursecdn.com/dota2.gamepedia.com/b/bc/Pain_pain_02.mp3"},{"others":[],"title":" Uh! ","url":"http://hydra-media.cursecdn.com/dota2.gamepedia.com/6/67/Pain_pain_03.mp3"},{"others":[],"title":" Oh! ","url":"http://hydra-media.cursecdn.com/dota2.gamepedia.com/d/d4/Pain_pain_04.mp3"},{"others":[],"title":" Ah! ","url":"http://hydra-media.cursecdn.com/dota2.gamepedia.com/a/a2/Pain_pain_05.mp3"},{"others":[],"title":" Ah! ","url":"http://hydra-media.cursecdn.com/dota2.gamepedia.com/c/cc/Pain_pain_06.mp3"},{"others":[],"title":" Ah! ","url":"http://hydra-media.cursecdn.com/dota2.gamepedia.com/f/f8/Pain_pain_07.mp3"},{"others":[],"title":" Ow! ","url":"http://hydra-media.cursecdn.com/dota2.gamepedia.com/0/07/Pain_pain_08.mp3"},{"others":[],"title":" Uh! ","url":"http://hydra-media.cursecdn.com/dota2.gamepedia.com/2/23/Pain_pain_09.mp3"},{"others":[],"title":" Oh! ","url":"http://hydra-media.cursecdn.com/dota2.gamepedia.com/c/c4/Pain_pain_10.mp3"},{"others":[],"title":" Ah! ","url":"http://hydra-media.cursecdn.com/dota2.gamepedia.com/1/16/Pain_pain_11.mp3"},{"others":[],"title":" Haaaaaa! ","url":"http://hydra-media.cursecdn.com/dota2.gamepedia.com/3/33/Pain_pain_12.mp3"},{"others":[],"title":" Haaaaaaaaaaaaaaauuuuuaaaa! ","url":"http://hydra-media.cursecdn.com/dota2.gamepedia.com/7/71/Pain_pain_13.mp3"},{"others":[],"title":" Haaaaaa! ","url":"http://hydra-media.cursecdn.com/dota2.gamepedia.com/a/a5/Pain_pain_14.mp3"},{"others":[],"title":" Huwaaaaa! ","url":"http://hydra-media.cursecdn.com/dota2.gamepedia.com/b/ba/Pain_pain_15.mp3"},{"others":[],"title":" Huwaaaa! ","url":"http://hydra-media.cursecdn.com/dota2.gamepedia.com/e/e6/Pain_pain_16.mp3"},{"others":[],"title":" Huwaaaaaaaaaaaaaaaaaaaaaaaaaaaa! ","url":"http://hydra-media.cursecdn.com/dota2.gamepedia.com/5/58/Pain_pain_17.mp3"},{"others":[],"title":" Uh. ","url":"http://hydra-media.cursecdn.com/dota2.gamepedia.com/5/59/Pain_anger_01.mp3"},{"others":[],"title":" Uh. ","url":"http://hydra-media.cursecdn.com/dota2.gamepedia.com/1/12/Pain_anger_02.mp3"},{"others":[],"title":" Muh! ","url":"http://hydra-media.cursecdn.com/dota2.gamepedia.com/9/97/Pain_anger_03.mp3"},{"others":[],"title":" Rar! ","url":"http://hydra-media.cursecdn.com/dota2.gamepedia.com/c/c6/Pain_anger_04.mp3"},{"others":[],"title":" Hm! ","url":"http://hydra-media.cursecdn.com/dota2.gamepedia.com/a/a2/Pain_happy_01.mp3"},{"others":[],"title":" Hm. ","url":"http://hydra-media.cursecdn.com/dota2.gamepedia.com/5/51/Pain_happy_02.mp3"},{"others":[],"title":" Ah! ","url":"http://hydra-media.cursecdn.com/dota2.gamepedia.com/b/bd/Pain_happy_03.mp3"},{"others":[],"title":" He ha ha ha ha ha ha! ","url":"http://hydra-media.cursecdn.com/dota2.gamepedia.com/1/16/Pain_laugh_01.mp3"},{"others":[],"title":" Hm ha ha ha ha ha ha ha ha ha ha ha ha ha ha ha ha! ","url":"http://hydra-media.cursecdn.com/dota2.gamepedia.com/4/43/Pain_laugh_02.mp3"},{"others":[],"title":" Uh ha ha ha ha! ","url":"http://hydra-media.cursecdn.com/dota2.gamepedia.com/5/57/Pain_laugh_03.mp3"},{"others":[],"title":" Uh ha ha ha ha ha ha ha ha ha ha ha! ","url":"http://hydra-media.cursecdn.com/dota2.gamepedia.com/1/1e/Pain_laugh_04.mp3"},{"others":[],"title":" Uh ha ha ha ha! ","url":"http://hydra-media.cursecdn.com/dota2.gamepedia.com/3/31/Pain_laugh_05.mp3"},{"others":[],"title":" Uh ha! ","url":"http://hydra-media.cursecdn.com/dota2.gamepedia.com/4/49/Pain_laugh_06.mp3"},{"others":[],"title":" Uh ha ha! ","url":"http://hydra-media.cursecdn.com/dota2.gamepedia.com/8/85/Pain_laugh_07.mp3"},{"others":[],"title":" Hm ha ha. ","url":"http://hydra-media.cursecdn.com/dota2.gamepedia.com/a/ae/Pain_laugh_08.mp3"},{"others":[],"title":" Uh, ha ha ha. ","url":"http://hydra-media.cursecdn.com/dota2.gamepedia.com/0/06/Pain_laugh_09.mp3"},{"others":[],"title":" Hm, ha ha ha ha! ","url":"http://hydra-media.cursecdn.com/dota2.gamepedia.com/c/c1/Pain_laugh_10.mp3"},{"others":[],"title":" Ha ha! ","url":"http://hydra-media.cursecdn.com/dota2.gamepedia.com/2/2d/Pain_laugh_11.mp3"},{"others":[],"title":" Uh ha ha ha! ","url":"http://hydra-media.cursecdn.com/dota2.gamepedia.com/1/1e/Pain_laugh_12.mp3"},{"others":[],"title":" Ha ha. ","url":"http://hydra-media.cursecdn.com/dota2.gamepedia.com/7/76/Pain_laugh_13.mp3"},{"others":[],"title":" Mu ha ha ha ha ha ha ha, he! ","url":"http://hydra-media.cursecdn.com/dota2.gamepedia.com/f/fb/Pain_laugh_14.mp3"},{"others":[],"title":" I\u0027m a strong believer in women\u0027s suffer-age. ","url":"http://hydra-media.cursecdn.com/dota2.gamepedia.com/a/ac/Pain_specialcase_02.mp3"},{"others":[],"title":" Done already? ","url":"http://hydra-media.cursecdn.com/dota2.gamepedia.com/7/73/Pain_specialcase_05.mp3"},{"others":["Skeleton King"],"title":" Skeleton King, could you feel something for me? ","url":"http://hydra-media.cursecdn.com/dota2.gamepedia.com/8/85/Pain_rival_12.mp3"}]}